split_screen_mcp/__init__.py
split_screen_mcp/__main__.py
split_screen_mcp/window_actions.py
split_screen_mac_test_mcp-1.2.0.dist-info/METADATA
split_screen_mac_test_mcp-1.2.0.dist-info/WHEEL
split_screen_mac_test_mcp-1.2.0.dist-info/entry_points.txt
split_screen_mac_test_mcp-1.2.0.dist-info/licenses/LICENSE
split_screen_mac_test_mcp-1.2.0.dist-info/RECORD
