Metadata-Version: 2.4
Name: split-screen-mac-test-mcp
Version: 1.2.0
Summary: Model Context Protocol Server for macOS Split Screen Window Management
Author: Beta
License: MIT License
License-File: LICENSE
Keywords: desktop-productivity,macos,mcp,split-screen,tiling,window-management
Requires-Python: >=3.9
Requires-Dist: mcp>=0.1.0
Requires-Dist: pyobjc-framework-appkit>=9.0; sys_platform == 'darwin'
Requires-Dist: pyobjc-framework-applicationservices>=9.0; sys_platform == 'darwin'
Requires-Dist: pyobjc-framework-quartz>=9.0; sys_platform == 'darwin'
